<settings version="0.0.2"   ><auto><configurations   /><panel>{"ext/editors/editors":{"parent":{"visible":2,"flex":1},"visible":2,"flex":1},"ext/tree/tree":{"parent":{"visible":2,"width":"200"},"visible":true,"flex":3,"state":"normal"},"ext/console/console":{"parent":{"visible":2,"height":200},"visible":true,"flex":1}}</panel><tree>["folder[1]","folder[1]/folder[2]","folder[1]/folder[2]/file[2]","folder[1]/folder[1]","folder[1]/folder[1]/file[3]","folder[1]/folder[2]/file[1]"]</tree><files active="/sunbox/mootools-fx-tween-css3/workspace/Source/Fx.Tween.CSS3.Replacement.js"><file path="/sunbox/mootools-fx-tween-css3/workspace/Source/Fx.Tween.CSS3.Replacement.js" type="file" size="4435" name="Fx.Tween.CSS3.Replacement.js" contenttype="application/javascript; charset=utf-8" creationdate="" lockable="false" hidden="false" executable="false" scriptname="/home/ide_sunbox/workspaces/mootools-fx-tween-css3/Source/Fx.Tween.CSS3.Replacement.js"/><file path="/sunbox/mootools-fx-tween-css3/workspace/Examples/test3.html" type="file" size="1384" name="test3.html" contenttype="text/html; charset=utf-8" creationdate="" lockable="false" hidden="false" executable="false" scriptname="/home/ide_sunbox/workspaces/mootools-fx-tween-css3/Examples/test3.html"/><file path="/sunbox/mootools-fx-tween-css3/workspace/Source/Fx.Tween.CSS3.js" type="file" size="4363" name="Fx.Tween.CSS3.js" contenttype="application/javascript; charset=utf-8" creationdate="" lockable="false" hidden="false" executable="false" scriptname="/home/ide_sunbox/workspaces/mootools-fx-tween-css3/Source/Fx.Tween.CSS3.js"/></files></auto><general name="General" page="pgSettingsGeneral" saveallbeforerun="true"/><editors name="Editor" page="pgSettingsEditors"><code name="Code Editor" overwrite="false" selectstyle="line" activeline="true" showinvisibles="false" showprintmargin="true" printmargincolumn="80" softtabs="true" tabsize="4" scrollspeed="2"/></editors></settings>